LICENSE
MANIFEST.in
README.md
setup.py
apidocs/__init__.py
apidocs/__version__.py
apidocs/apps.py
apidocs/base.py
apidocs/checks.py
apidocs/decorators.py
apidocs/handler.py
apidocs/routers.py
apidocs/settings.py
apidocs/urls.py
apidocs/view.py
apidocs.egg-info/PKG-INFO
apidocs.egg-info/SOURCES.txt
apidocs.egg-info/dependency_links.txt
apidocs.egg-info/top_level.txt